{
  "target": {
    "type": "title",
    "title": "\\(\\d+?\\/\\d+?\\) Experimentation Table RNG"
  },
  "layout": [
    {
      "id": "skyblock_gui:rng_meter/icon/experimentation_table",
      "target": {
        "type": "name",
        "mode": "equals",
        "name": "RNG Meter"
      }
    },
    {
      "id": "skyblock_gui:rng_meter/experimentation_table/icon/reset_rng_drop",
      "target": {
        "type": "name",
        "mode": "equals",
        "name": "Reset RNG Drop"
      }
    }
  ]
}
