{
  "target": {
    "title": "Moonflower Collection",
    "type": "catharsis:title"
  },
  "layout": [
    {
      "id": "skyblock_gui:collections/farming/unlocked/start",
      "target": {
        "conditions": [
          {
            "slot": 18,
            "type": "catharsis:slot"
          },
          {
            "items": "minecraft:lime_stained_glass_pane",
            "type": "catharsis:item"
          },
          {
            "name": [
              "Moonflower 1",
              "Moonflower I"
            ],
            "mode": "equals",
            "type": "catharsis:name"
          }
        ],
        "type": "catharsis:all"
      }
    },
    {
      "id": "skyblock_gui:collections/farming/unlocking/start",
      "target": {
        "conditions": [
          {
            "slot": 18,
            "type": "catharsis:slot"
          },
          {
            "items": "minecraft:yellow_stained_glass_pane",
            "type": "catharsis:item"
          },
          {
            "name": [
              "Moonflower 1",
              "Moonflower I"
            ],
            "mode": "equals",
            "type": "catharsis:name"
          }
        ],
        "type": "catharsis:all"
      }
    },
    {
      "id": "skyblock_gui:collections/farming/locked/start",
      "target": {
        "conditions": [
          {
            "slot": 18,
            "type": "catharsis:slot"
          },
          {
            "items": "minecraft:red_stained_glass_pane",
            "type": "catharsis:item"
          },
          {
            "name": [
              "Moonflower 1",
              "Moonflower I"
            ],
            "mode": "equals",
            "type": "catharsis:name"
          }
        ],
        "type": "catharsis:all"
      }
    },
    {
      "id": "skyblock_gui:collections/farming/unlocked/connector",
      "target": {
        "conditions": [
          {
            "slot": 19,
            "type": "catharsis:slot"
          },
          {
            "items": "minecraft:lime_stained_glass_pane",
            "type": "catharsis:item"
          },
          {
            "name": [
              "Moonflower 2",
              "Moonflower II"
            ],
            "mode": "equals",
            "type": "catharsis:name"
          }
        ],
        "type": "catharsis:all"
      }
    },
    {
      "id": "skyblock_gui:collections/farming/unlocking/connector",
      "target": {
        "conditions": [
          {
            "slot": 19,
            "type": "catharsis:slot"
          },
          {
            "items": "minecraft:yellow_stained_glass_pane",
            "type": "catharsis:item"
          },
          {
            "name": [
              "Moonflower 2",
              "Moonflower II"
            ],
            "mode": "equals",
            "type": "catharsis:name"
          }
        ],
        "type": "catharsis:all"
      }
    },
    {
      "id": "skyblock_gui:collections/farming/locked/connector",
      "target": {
        "conditions": [
          {
            "slot": 19,
            "type": "catharsis:slot"
          },
          {
            "items": "minecraft:red_stained_glass_pane",
            "type": "catharsis:item"
          },
          {
            "name": [
              "Moonflower 2",
              "Moonflower II"
            ],
            "mode": "equals",
            "type": "catharsis:name"
          }
        ],
        "type": "catharsis:all"
      }
    },
    {
      "id": "skyblock_gui:collections/farming/unlocked/connector",
      "target": {
        "conditions": [
          {
            "slot": 20,
            "type": "catharsis:slot"
          },
          {
            "items": "minecraft:lime_stained_glass_pane",
            "type": "catharsis:item"
          },
          {
            "name": [
              "Moonflower 3",
              "Moonflower III"
            ],
            "mode": "equals",
            "type": "catharsis:name"
          }
        ],
        "type": "catharsis:all"
      }
    },
    {
      "id": "skyblock_gui:collections/farming/unlocking/connector",
      "target": {
        "conditions": [
          {
            "slot": 20,
            "type": "catharsis:slot"
          },
          {
            "items": "minecraft:yellow_stained_glass_pane",
            "type": "catharsis:item"
          },
          {
            "name": [
              "Moonflower 3",
              "Moonflower III"
            ],
            "mode": "equals",
            "type": "catharsis:name"
          }
        ],
        "type": "catharsis:all"
      }
    },
    {
      "id": "skyblock_gui:collections/farming/locked/connector",
      "target": {
        "conditions": [
          {
            "slot": 20,
            "type": "catharsis:slot"
          },
          {
            "items": "minecraft:red_stained_glass_pane",
            "type": "catharsis:item"
          },
          {
            "name": [
              "Moonflower 3",
              "Moonflower III"
            ],
            "mode": "equals",
            "type": "catharsis:name"
          }
        ],
        "type": "catharsis:all"
      }
    },
    {
      "id": "skyblock_gui:collections/farming/unlocked/connector_skip",
      "target": {
        "conditions": [
          {
            "slot": 21,
            "type": "catharsis:slot"
          },
          {
            "items": "minecraft:lime_stained_glass_pane",
            "type": "catharsis:item"
          },
          {
            "name": [
              "Moonflower 4",
              "Moonflower IV"
            ],
            "mode": "equals",
            "type": "catharsis:name"
          }
        ],
        "type": "catharsis:all"
      }
    },
    {
      "id": "skyblock_gui:collections/farming/unlocking/connector_skip",
      "target": {
        "conditions": [
          {
            "slot": 21,
            "type": "catharsis:slot"
          },
          {
            "items": "minecraft:yellow_stained_glass_pane",
            "type": "catharsis:item"
          },
          {
            "name": [
              "Moonflower 4",
              "Moonflower IV"
            ],
            "mode": "equals",
            "type": "catharsis:name"
          }
        ],
        "type": "catharsis:all"
      }
    },
    {
      "id": "skyblock_gui:collections/farming/locked/connector_skip",
      "target": {
        "conditions": [
          {
            "slot": 21,
            "type": "catharsis:slot"
          },
          {
            "items": "minecraft:red_stained_glass_pane",
            "type": "catharsis:item"
          },
          {
            "name": [
              "Moonflower 4",
              "Moonflower IV"
            ],
            "mode": "equals",
            "type": "catharsis:name"
          }
        ],
        "type": "catharsis:all"
      }
    },
    {
      "id": "skyblock_gui:collections/farming/unlocked/skip_connector",
      "target": {
        "conditions": [
          {
            "slot": 23,
            "type": "catharsis:slot"
          },
          {
            "items": "minecraft:lime_stained_glass_pane",
            "type": "catharsis:item"
          },
          {
            "name": [
              "Moonflower 5",
              "Moonflower V"
            ],
            "mode": "equals",
            "type": "catharsis:name"
          }
        ],
        "type": "catharsis:all"
      }
    },
    {
      "id": "skyblock_gui:collections/farming/unlocking/skip_connector",
      "target": {
        "conditions": [
          {
            "slot": 23,
            "type": "catharsis:slot"
          },
          {
            "items": "minecraft:yellow_stained_glass_pane",
            "type": "catharsis:item"
          },
          {
            "name": [
              "Moonflower 5",
              "Moonflower V"
            ],
            "mode": "equals",
            "type": "catharsis:name"
          }
        ],
        "type": "catharsis:all"
      }
    },
    {
      "id": "skyblock_gui:collections/farming/locked/skip_connector",
      "target": {
        "conditions": [
          {
            "slot": 23,
            "type": "catharsis:slot"
          },
          {
            "items": "minecraft:red_stained_glass_pane",
            "type": "catharsis:item"
          },
          {
            "name": [
              "Moonflower 5",
              "Moonflower V"
            ],
            "mode": "equals",
            "type": "catharsis:name"
          }
        ],
        "type": "catharsis:all"
      }
    },
    {
      "id": "skyblock_gui:collections/farming/unlocked/connector",
      "target": {
        "conditions": [
          {
            "slot": 24,
            "type": "catharsis:slot"
          },
          {
            "items": "minecraft:lime_stained_glass_pane",
            "type": "catharsis:item"
          },
          {
            "name": [
              "Moonflower 6",
              "Moonflower VI"
            ],
            "mode": "equals",
            "type": "catharsis:name"
          }
        ],
        "type": "catharsis:all"
      }
    },
    {
      "id": "skyblock_gui:collections/farming/unlocking/connector",
      "target": {
        "conditions": [
          {
            "slot": 24,
            "type": "catharsis:slot"
          },
          {
            "items": "minecraft:yellow_stained_glass_pane",
            "type": "catharsis:item"
          },
          {
            "name": [
              "Moonflower 6",
              "Moonflower VI"
            ],
            "mode": "equals",
            "type": "catharsis:name"
          }
        ],
        "type": "catharsis:all"
      }
    },
    {
      "id": "skyblock_gui:collections/farming/locked/connector",
      "target": {
        "conditions": [
          {
            "slot": 24,
            "type": "catharsis:slot"
          },
          {
            "items": "minecraft:red_stained_glass_pane",
            "type": "catharsis:item"
          },
          {
            "name": [
              "Moonflower 6",
              "Moonflower VI"
            ],
            "mode": "equals",
            "type": "catharsis:name"
          }
        ],
        "type": "catharsis:all"
      }
    },
    {
      "id": "skyblock_gui:collections/farming/unlocked/connector",
      "target": {
        "conditions": [
          {
            "slot": 25,
            "type": "catharsis:slot"
          },
          {
            "items": "minecraft:lime_stained_glass_pane",
            "type": "catharsis:item"
          },
          {
            "name": [
              "Moonflower 7",
              "Moonflower VII"
            ],
            "mode": "equals",
            "type": "catharsis:name"
          }
        ],
        "type": "catharsis:all"
      }
    },
    {
      "id": "skyblock_gui:collections/farming/unlocking/connector",
      "target": {
        "conditions": [
          {
            "slot": 25,
            "type": "catharsis:slot"
          },
          {
            "items": "minecraft:yellow_stained_glass_pane",
            "type": "catharsis:item"
          },
          {
            "name": [
              "Moonflower 7",
              "Moonflower VII"
            ],
            "mode": "equals",
            "type": "catharsis:name"
          }
        ],
        "type": "catharsis:all"
      }
    },
    {
      "id": "skyblock_gui:collections/farming/locked/connector",
      "target": {
        "conditions": [
          {
            "slot": 25,
            "type": "catharsis:slot"
          },
          {
            "items": "minecraft:red_stained_glass_pane",
            "type": "catharsis:item"
          },
          {
            "name": [
              "Moonflower 7",
              "Moonflower VII"
            ],
            "mode": "equals",
            "type": "catharsis:name"
          }
        ],
        "type": "catharsis:all"
      }
    },
    {
      "id": "skyblock_gui:collections/farming/unlocked/end",
      "target": {
        "conditions": [
          {
            "slot": 26,
            "type": "catharsis:slot"
          },
          {
            "items": "minecraft:lime_stained_glass_pane",
            "type": "catharsis:item"
          },
          {
            "name": [
              "Moonflower 8",
              "Moonflower VIII"
            ],
            "mode": "equals",
            "type": "catharsis:name"
          }
        ],
        "type": "catharsis:all"
      }
    },
    {
      "id": "skyblock_gui:collections/farming/unlocking/end",
      "target": {
        "conditions": [
          {
            "slot": 26,
            "type": "catharsis:slot"
          },
          {
            "items": "minecraft:yellow_stained_glass_pane",
            "type": "catharsis:item"
          },
          {
            "name": [
              "Moonflower 8",
              "Moonflower VIII"
            ],
            "mode": "equals",
            "type": "catharsis:name"
          }
        ],
        "type": "catharsis:all"
      }
    },
    {
      "id": "skyblock_gui:collections/farming/locked/end",
      "target": {
        "conditions": [
          {
            "slot": 26,
            "type": "catharsis:slot"
          },
          {
            "items": "minecraft:red_stained_glass_pane",
            "type": "catharsis:item"
          },
          {
            "name": [
              "Moonflower 8",
              "Moonflower VIII"
            ],
            "mode": "equals",
            "type": "catharsis:name"
          }
        ],
        "type": "catharsis:all"
      }
    }
  ]
}