{
  "target": {
    "type": "title",
    "title": "Tank Class Perks"
  },
  "layout": [
    {
      "id": "skyblock_gui:classes/tank/icon",
      "target": {
        "type": "all",
        "conditions": [
          {
            "type": "name",
            "name": "Tank Class"
          },
          {
            "type": "slot",
            "slot": 0
          }
        ]
      }
    },
    {
      "id": "skyblock_gui:classes/tank/unlocked/start_down",
      "target": {
        "type": "all",
        "conditions": [
          {
            "type": "item",
            "items": [
              "lime_stained_glass_pane"
            ]
          },
          {
            "type": "name",
            "mode": "equals",
            "name": [
              "Tank Level I",
              "Tank Level 1"
            ]
          }
        ]
      }
    },
    {
      "id": "skyblock_gui:classes/tank/unlocking/start_down",
      "target": {
        "type": "all",
        "conditions": [
          {
            "type": "item",
            "items": "yellow_stained_glass_pane"
          },
          {
            "type": "name",
            "mode": "equals",
            "name": [
              "Tank Level I",
              "Tank Level 1"
            ]
          }
        ]
      }
    },
    {
      "id": "skyblock_gui:classes/tank/locked/start_down",
      "target": {
        "type": "all",
        "conditions": [
          {
            "type": "item",
            "items": "red_stained_glass_pane"
          },
          {
            "type": "name",
            "mode": "equals",
            "name": [
              "Tank Level I",
              "Tank Level 1"
            ]
          }
        ]
      }
    },
    {
      "id": "skyblock_gui:classes/tank/unlocked/up_down",
      "target": {
        "type": "all",
        "conditions": [
          {
            "type": "item",
            "items": [
              "lime_stained_glass_pane"
            ]
          },
          {
            "type": "name",
            "mode": "equals",
            "name": [
              "Tank Level II",
              "Tank Level 2"
            ]
          }
        ]
      }
    },
    {
      "id": "skyblock_gui:classes/tank/unlocking/up_down",
      "target": {
        "type": "all",
        "conditions": [
          {
            "type": "item",
            "items": "yellow_stained_glass_pane"
          },
          {
            "type": "name",
            "mode": "equals",
            "name": [
              "Tank Level II",
              "Tank Level 2"
            ]
          }
        ]
      }
    },
    {
      "id": "skyblock_gui:classes/tank/locked/up_down",
      "target": {
        "type": "all",
        "conditions": [
          {
            "type": "item",
            "items": "red_stained_glass_pane"
          },
          {
            "type": "name",
            "mode": "equals",
            "name": [
              "Tank Level II",
              "Tank Level 2"
            ]
          }
        ]
      }
    },
    {
      "id": "skyblock_gui:classes/tank/unlocked/up_right",
      "target": {
        "type": "all",
        "conditions": [
          {
            "type": "item",
            "items": [
              "lime_stained_glass_pane"
            ]
          },
          {
            "type": "name",
            "mode": "equals",
            "name": [
              "Tank Level III",
              "Tank Level 3"
            ]
          }
        ]
      }
    },
    {
      "id": "skyblock_gui:classes/tank/unlocking/up_right",
      "target": {
        "type": "all",
        "conditions": [
          {
            "type": "item",
            "items": "yellow_stained_glass_pane"
          },
          {
            "type": "name",
            "mode": "equals",
            "name": [
              "Tank Level III",
              "Tank Level 3"
            ]
          }
        ]
      }
    },
    {
      "id": "skyblock_gui:classes/tank/locked/up_right",
      "target": {
        "type": "all",
        "conditions": [
          {
            "type": "item",
            "items": "red_stained_glass_pane"
          },
          {
            "type": "name",
            "mode": "equals",
            "name": [
              "Tank Level III",
              "Tank Level 3"
            ]
          }
        ]
      }
    },
    {
      "id": "skyblock_gui:classes/tank/unlocked/left_right",
      "target": {
        "type": "all",
        "conditions": [
          {
            "type": "item",
            "items": [
              "lime_stained_glass_pane"
            ]
          },
          {
            "type": "name",
            "mode": "equals",
            "name": [
              "Tank Level IV",
              "Tank Level 4"
            ]
          }
        ]
      }
    },
    {
      "id": "skyblock_gui:classes/tank/unlocking/left_right",
      "target": {
        "type": "all",
        "conditions": [
          {
            "type": "item",
            "items": "yellow_stained_glass_pane"
          },
          {
            "type": "name",
            "mode": "equals",
            "name": [
              "Tank Level IV",
              "Tank Level 4"
            ]
          }
        ]
      }
    },
    {
      "id": "skyblock_gui:classes/tank/locked/left_right",
      "target": {
        "type": "all",
        "conditions": [
          {
            "type": "item",
            "items": "red_stained_glass_pane"
          },
          {
            "type": "name",
            "mode": "equals",
            "name": [
              "Tank Level IV",
              "Tank Level 4"
            ]
          }
        ]
      }
    },
    {
      "id": "skyblock_gui:classes/tank/unlocked/left_up",
      "target": {
        "type": "all",
        "conditions": [
          {
            "type": "item",
            "items": [
              "lime_stained_glass_pane",
              "leather_chestplate"
            ]
          },
          {
            "type": "name",
            "mode": "equals",
            "name": [
              "Tank Level V",
              "Tank Level 5"
            ]
          }
        ]
      }
    },
    {
      "id": "skyblock_gui:classes/tank/unlocking/left_up",
      "target": {
        "type": "all",
        "conditions": [
          {
            "type": "item",
            "items": "yellow_stained_glass_pane"
          },
          {
            "type": "name",
            "mode": "equals",
            "name": [
              "Tank Level V",
              "Tank Level 5"
            ]
          }
        ]
      }
    },
    {
      "id": "skyblock_gui:classes/tank/locked/left_up",
      "target": {
        "type": "all",
        "conditions": [
          {
            "type": "item",
            "items": "red_stained_glass_pane"
          },
          {
            "type": "name",
            "mode": "equals",
            "name": [
              "Tank Level V",
              "Tank Level 5"
            ]
          }
        ]
      }
    },
    {
      "id": "skyblock_gui:classes/tank/unlocked/down_up",
      "target": {
        "type": "all",
        "conditions": [
          {
            "type": "item",
            "items": [
              "lime_stained_glass_pane"
            ]
          },
          {
            "type": "name",
            "mode": "equals",
            "name": [
              "Tank Level VI",
              "Tank Level 6"
            ]
          }
        ]
      }
    },
    {
      "id": "skyblock_gui:classes/tank/unlocking/down_up",
      "target": {
        "type": "all",
        "conditions": [
          {
            "type": "item",
            "items": "yellow_stained_glass_pane"
          },
          {
            "type": "name",
            "mode": "equals",
            "name": [
              "Tank Level VI",
              "Tank Level 6"
            ]
          }
        ]
      }
    },
    {
      "id": "skyblock_gui:classes/tank/locked/down_up",
      "target": {
        "type": "all",
        "conditions": [
          {
            "type": "item",
            "items": "red_stained_glass_pane"
          },
          {
            "type": "name",
            "mode": "equals",
            "name": [
              "Tank Level VI",
              "Tank Level 6"
            ]
          }
        ]
      }
    },
    {
      "id": "skyblock_gui:classes/tank/unlocked/down_up",
      "target": {
        "type": "all",
        "conditions": [
          {
            "type": "item",
            "items": [
              "lime_stained_glass_pane"
            ]
          },
          {
            "type": "name",
            "mode": "equals",
            "name": [
              "Tank Level VII",
              "Tank Level 7"
            ]
          }
        ]
      }
    },
    {
      "id": "skyblock_gui:classes/tank/unlocking/down_up",
      "target": {
        "type": "all",
        "conditions": [
          {
            "type": "item",
            "items": "yellow_stained_glass_pane"
          },
          {
            "type": "name",
            "mode": "equals",
            "name": [
              "Tank Level VII",
              "Tank Level 7"
            ]
          }
        ]
      }
    },
    {
      "id": "skyblock_gui:classes/tank/locked/down_up",
      "target": {
        "type": "all",
        "conditions": [
          {
            "type": "item",
            "items": "red_stained_glass_pane"
          },
          {
            "type": "name",
            "mode": "equals",
            "name": [
              "Tank Level VII",
              "Tank Level 7"
            ]
          }
        ]
      }
    },
    {
      "id": "skyblock_gui:classes/tank/unlocked/down_right",
      "target": {
        "type": "all",
        "conditions": [
          {
            "type": "item",
            "items": [
              "lime_stained_glass_pane"
            ]
          },
          {
            "type": "name",
            "mode": "equals",
            "name": [
              "Tank Level VIII",
              "Tank Level 8"
            ]
          }
        ]
      }
    },
    {
      "id": "skyblock_gui:classes/tank/unlocking/down_right",
      "target": {
        "type": "all",
        "conditions": [
          {
            "type": "item",
            "items": "yellow_stained_glass_pane"
          },
          {
            "type": "name",
            "mode": "equals",
            "name": [
              "Tank Level VIII",
              "Tank Level 8"
            ]
          }
        ]
      }
    },
    {
      "id": "skyblock_gui:classes/tank/locked/down_right",
      "target": {
        "type": "all",
        "conditions": [
          {
            "type": "item",
            "items": "red_stained_glass_pane"
          },
          {
            "type": "name",
            "mode": "equals",
            "name": [
              "Tank Level VIII",
              "Tank Level 8"
            ]
          }
        ]
      }
    },
    {
      "id": "skyblock_gui:classes/tank/unlocked/left_right",
      "target": {
        "type": "all",
        "conditions": [
          {
            "type": "item",
            "items": [
              "lime_stained_glass_pane"
            ]
          },
          {
            "type": "name",
            "mode": "equals",
            "name": [
              "Tank Level IX",
              "Tank Level 9"
            ]
          }
        ]
      }
    },
    {
      "id": "skyblock_gui:classes/tank/unlocking/left_right",
      "target": {
        "type": "all",
        "conditions": [
          {
            "type": "item",
            "items": "yellow_stained_glass_pane"
          },
          {
            "type": "name",
            "mode": "equals",
            "name": [
              "Tank Level IX",
              "Tank Level 9"
            ]
          }
        ]
      }
    },
    {
      "id": "skyblock_gui:classes/tank/locked/left_right",
      "target": {
        "type": "all",
        "conditions": [
          {
            "type": "item",
            "items": "red_stained_glass_pane"
          },
          {
            "type": "name",
            "mode": "equals",
            "name": [
              "Tank Level IX",
              "Tank Level 9"
            ]
          }
        ]
      }
    },
    {
      "id": "skyblock_gui:classes/tank/unlocked/left_down",
      "target": {
        "type": "all",
        "conditions": [
          {
            "type": "item",
            "items": [
              "lime_stained_glass_pane",
              "leather_chestplate"
            ]
          },
          {
            "type": "name",
            "mode": "equals",
            "name": [
              "Tank Level X",
              "Tank Level 10"
            ]
          }
        ]
      }
    },
    {
      "id": "skyblock_gui:classes/tank/unlocking/left_down",
      "target": {
        "type": "all",
        "conditions": [
          {
            "type": "item",
            "items": "yellow_stained_glass_pane"
          },
          {
            "type": "name",
            "mode": "equals",
            "name": [
              "Tank Level X",
              "Tank Level 10"
            ]
          }
        ]
      }
    },
    {
      "id": "skyblock_gui:classes/tank/locked/left_down",
      "target": {
        "type": "all",
        "conditions": [
          {
            "type": "item",
            "items": "red_stained_glass_pane"
          },
          {
            "type": "name",
            "mode": "equals",
            "name": [
              "Tank Level X",
              "Tank Level 10"
            ]
          }
        ]
      }
    },
    {
      "id": "skyblock_gui:classes/tank/unlocked/up_down",
      "target": {
        "type": "all",
        "conditions": [
          {
            "type": "item",
            "items": [
              "lime_stained_glass_pane"
            ]
          },
          {
            "type": "name",
            "mode": "equals",
            "name": [
              "Tank Level XI",
              "Tank Level 11"
            ]
          }
        ]
      }
    },
    {
      "id": "skyblock_gui:classes/tank/unlocking/up_down",
      "target": {
        "type": "all",
        "conditions": [
          {
            "type": "item",
            "items": "yellow_stained_glass_pane"
          },
          {
            "type": "name",
            "mode": "equals",
            "name": [
              "Tank Level XI",
              "Tank Level 11"
            ]
          }
        ]
      }
    },
    {
      "id": "skyblock_gui:classes/tank/locked/up_down",
      "target": {
        "type": "all",
        "conditions": [
          {
            "type": "item",
            "items": "red_stained_glass_pane"
          },
          {
            "type": "name",
            "mode": "equals",
            "name": [
              "Tank Level XI",
              "Tank Level 11"
            ]
          }
        ]
      }
    },
    {
      "id": "skyblock_gui:classes/tank/unlocked/up_down",
      "target": {
        "type": "all",
        "conditions": [
          {
            "type": "item",
            "items": [
              "lime_stained_glass_pane"
            ]
          },
          {
            "type": "name",
            "mode": "equals",
            "name": [
              "Tank Level XII",
              "Tank Level 12"
            ]
          }
        ]
      }
    },
    {
      "id": "skyblock_gui:classes/tank/unlocking/up_down",
      "target": {
        "type": "all",
        "conditions": [
          {
            "type": "item",
            "items": "yellow_stained_glass_pane"
          },
          {
            "type": "name",
            "mode": "equals",
            "name": [
              "Tank Level XII",
              "Tank Level 12"
            ]
          }
        ]
      }
    },
    {
      "id": "skyblock_gui:classes/tank/locked/up_down",
      "target": {
        "type": "all",
        "conditions": [
          {
            "type": "item",
            "items": "red_stained_glass_pane"
          },
          {
            "type": "name",
            "mode": "equals",
            "name": [
              "Tank Level XII",
              "Tank Level 12"
            ]
          }
        ]
      }
    },
    {
      "id": "skyblock_gui:classes/tank/unlocked/up_right",
      "target": {
        "type": "all",
        "conditions": [
          {
            "type": "item",
            "items": [
              "lime_stained_glass_pane"
            ]
          },
          {
            "type": "name",
            "mode": "equals",
            "name": [
              "Tank Level XIII",
              "Tank Level 13"
            ]
          }
        ]
      }
    },
    {
      "id": "skyblock_gui:classes/tank/unlocking/up_right",
      "target": {
        "type": "all",
        "conditions": [
          {
            "type": "item",
            "items": "yellow_stained_glass_pane"
          },
          {
            "type": "name",
            "mode": "equals",
            "name": [
              "Tank Level XIII",
              "Tank Level 13"
            ]
          }
        ]
      }
    },
    {
      "id": "skyblock_gui:classes/tank/locked/up_right",
      "target": {
        "type": "all",
        "conditions": [
          {
            "type": "item",
            "items": "red_stained_glass_pane"
          },
          {
            "type": "name",
            "mode": "equals",
            "name": [
              "Tank Level XIII",
              "Tank Level 13"
            ]
          }
        ]
      }
    },
    {
      "id": "skyblock_gui:classes/tank/unlocked/left_right",
      "target": {
        "type": "all",
        "conditions": [
          {
            "type": "item",
            "items": [
              "lime_stained_glass_pane"
            ]
          },
          {
            "type": "name",
            "mode": "equals",
            "name": [
              "Tank Level XIV",
              "Tank Level 14"
            ]
          }
        ]
      }
    },
    {
      "id": "skyblock_gui:classes/tank/unlocking/left_right",
      "target": {
        "type": "all",
        "conditions": [
          {
            "type": "item",
            "items": "yellow_stained_glass_pane"
          },
          {
            "type": "name",
            "mode": "equals",
            "name": [
              "Tank Level XIV",
              "Tank Level 14"
            ]
          }
        ]
      }
    },
    {
      "id": "skyblock_gui:classes/tank/locked/left_right",
      "target": {
        "type": "all",
        "conditions": [
          {
            "type": "item",
            "items": "red_stained_glass_pane"
          },
          {
            "type": "name",
            "mode": "equals",
            "name": [
              "Tank Level XIV",
              "Tank Level 14"
            ]
          }
        ]
      }
    },
    {
      "id": "skyblock_gui:classes/tank/unlocked/left_up",
      "target": {
        "type": "all",
        "conditions": [
          {
            "type": "item",
            "items": [
              "lime_stained_glass_pane",
              "leather_chestplate"
            ]
          },
          {
            "type": "name",
            "mode": "equals",
            "name": [
              "Tank Level XV",
              "Tank Level 15"
            ]
          }
        ]
      }
    },
    {
      "id": "skyblock_gui:classes/tank/unlocking/left_up",
      "target": {
        "type": "all",
        "conditions": [
          {
            "type": "item",
            "items": "yellow_stained_glass_pane"
          },
          {
            "type": "name",
            "mode": "equals",
            "name": [
              "Tank Level XV",
              "Tank Level 15"
            ]
          }
        ]
      }
    },
    {
      "id": "skyblock_gui:classes/tank/locked/left_up",
      "target": {
        "type": "all",
        "conditions": [
          {
            "type": "item",
            "items": "red_stained_glass_pane"
          },
          {
            "type": "name",
            "mode": "equals",
            "name": [
              "Tank Level XV",
              "Tank Level 15"
            ]
          }
        ]
      }
    },
    {
      "id": "skyblock_gui:classes/tank/unlocked/down_up",
      "target": {
        "type": "all",
        "conditions": [
          {
            "type": "item",
            "items": [
              "lime_stained_glass_pane"
            ]
          },
          {
            "type": "name",
            "mode": "equals",
            "name": [
              "Tank Level XVI",
              "Tank Level 16"
            ]
          }
        ]
      }
    },
    {
      "id": "skyblock_gui:classes/tank/unlocking/down_up",
      "target": {
        "type": "all",
        "conditions": [
          {
            "type": "item",
            "items": "yellow_stained_glass_pane"
          },
          {
            "type": "name",
            "mode": "equals",
            "name": [
              "Tank Level XVI",
              "Tank Level 16"
            ]
          }
        ]
      }
    },
    {
      "id": "skyblock_gui:classes/tank/locked/down_up",
      "target": {
        "type": "all",
        "conditions": [
          {
            "type": "item",
            "items": "red_stained_glass_pane"
          },
          {
            "type": "name",
            "mode": "equals",
            "name": [
              "Tank Level XVI",
              "Tank Level 16"
            ]
          }
        ]
      }
    },
    {
      "id": "skyblock_gui:classes/tank/unlocked/down_up",
      "target": {
        "type": "all",
        "conditions": [
          {
            "type": "item",
            "items": [
              "lime_stained_glass_pane"
            ]
          },
          {
            "type": "name",
            "mode": "equals",
            "name": [
              "Tank Level XVII",
              "Tank Level 17"
            ]
          }
        ]
      }
    },
    {
      "id": "skyblock_gui:classes/tank/unlocking/down_up",
      "target": {
        "type": "all",
        "conditions": [
          {
            "type": "item",
            "items": "yellow_stained_glass_pane"
          },
          {
            "type": "name",
            "mode": "equals",
            "name": [
              "Tank Level XVII",
              "Tank Level 17"
            ]
          }
        ]
      }
    },
    {
      "id": "skyblock_gui:classes/tank/locked/down_up",
      "target": {
        "type": "all",
        "conditions": [
          {
            "type": "item",
            "items": "red_stained_glass_pane"
          },
          {
            "type": "name",
            "mode": "equals",
            "name": [
              "Tank Level XVII",
              "Tank Level 17"
            ]
          }
        ]
      }
    },
    {
      "id": "skyblock_gui:classes/tank/unlocked/down_right",
      "target": {
        "type": "all",
        "conditions": [
          {
            "type": "item",
            "items": [
              "lime_stained_glass_pane"
            ]
          },
          {
            "type": "name",
            "mode": "equals",
            "name": [
              "Tank Level XVIII",
              "Tank Level 18"
            ]
          }
        ]
      }
    },
    {
      "id": "skyblock_gui:classes/tank/unlocking/down_right",
      "target": {
        "type": "all",
        "conditions": [
          {
            "type": "item",
            "items": "yellow_stained_glass_pane"
          },
          {
            "type": "name",
            "mode": "equals",
            "name": [
              "Tank Level XVIII",
              "Tank Level 18"
            ]
          }
        ]
      }
    },
    {
      "id": "skyblock_gui:classes/tank/locked/down_right",
      "target": {
        "type": "all",
        "conditions": [
          {
            "type": "item",
            "items": "red_stained_glass_pane"
          },
          {
            "type": "name",
            "mode": "equals",
            "name": [
              "Tank Level XVIII",
              "Tank Level 18"
            ]
          }
        ]
      }
    },
    {
      "id": "skyblock_gui:classes/tank/unlocked/left_right",
      "target": {
        "type": "all",
        "conditions": [
          {
            "type": "item",
            "items": [
              "lime_stained_glass_pane"
            ]
          },
          {
            "type": "name",
            "mode": "equals",
            "name": [
              "Tank Level XIX",
              "Tank Level 19"
            ]
          }
        ]
      }
    },
    {
      "id": "skyblock_gui:classes/tank/unlocking/left_right",
      "target": {
        "type": "all",
        "conditions": [
          {
            "type": "item",
            "items": "yellow_stained_glass_pane"
          },
          {
            "type": "name",
            "mode": "equals",
            "name": [
              "Tank Level XIX",
              "Tank Level 19"
            ]
          }
        ]
      }
    },
    {
      "id": "skyblock_gui:classes/tank/locked/left_right",
      "target": {
        "type": "all",
        "conditions": [
          {
            "type": "item",
            "items": "red_stained_glass_pane"
          },
          {
            "type": "name",
            "mode": "equals",
            "name": [
              "Tank Level XIX",
              "Tank Level 19"
            ]
          }
        ]
      }
    },
    {
      "id": "skyblock_gui:classes/tank/unlocked/left_down",
      "target": {
        "type": "all",
        "conditions": [
          {
            "type": "item",
            "items": [
              "lime_stained_glass_pane",
              "leather_chestplate"
            ]
          },
          {
            "type": "name",
            "mode": "equals",
            "name": [
              "Tank Level XX",
              "Tank Level 20"
            ]
          }
        ]
      }
    },
    {
      "id": "skyblock_gui:classes/tank/unlocking/left_down",
      "target": {
        "type": "all",
        "conditions": [
          {
            "type": "item",
            "items": "yellow_stained_glass_pane"
          },
          {
            "type": "name",
            "mode": "equals",
            "name": [
              "Tank Level XX",
              "Tank Level 20"
            ]
          }
        ]
      }
    },
    {
      "id": "skyblock_gui:classes/tank/locked/left_down",
      "target": {
        "type": "all",
        "conditions": [
          {
            "type": "item",
            "items": "red_stained_glass_pane"
          },
          {
            "type": "name",
            "mode": "equals",
            "name": [
              "Tank Level XX",
              "Tank Level 20"
            ]
          }
        ]
      }
    },
    {
      "id": "skyblock_gui:classes/tank/unlocked/up_down",
      "target": {
        "type": "all",
        "conditions": [
          {
            "type": "item",
            "items": [
              "lime_stained_glass_pane"
            ]
          },
          {
            "type": "name",
            "mode": "equals",
            "name": [
              "Tank Level XXI",
              "Tank Level 21"
            ]
          }
        ]
      }
    },
    {
      "id": "skyblock_gui:classes/tank/unlocking/up_down",
      "target": {
        "type": "all",
        "conditions": [
          {
            "type": "item",
            "items": "yellow_stained_glass_pane"
          },
          {
            "type": "name",
            "mode": "equals",
            "name": [
              "Tank Level XXI",
              "Tank Level 21"
            ]
          }
        ]
      }
    },
    {
      "id": "skyblock_gui:classes/tank/locked/up_down",
      "target": {
        "type": "all",
        "conditions": [
          {
            "type": "item",
            "items": "red_stained_glass_pane"
          },
          {
            "type": "name",
            "mode": "equals",
            "name": [
              "Tank Level XXI",
              "Tank Level 21"
            ]
          }
        ]
      }
    },
    {
      "id": "skyblock_gui:classes/tank/unlocked/up_down",
      "target": {
        "type": "all",
        "conditions": [
          {
            "type": "item",
            "items": [
              "lime_stained_glass_pane"
            ]
          },
          {
            "type": "name",
            "mode": "equals",
            "name": [
              "Tank Level XXII",
              "Tank Level 22"
            ]
          }
        ]
      }
    },
    {
      "id": "skyblock_gui:classes/tank/unlocking/up_down",
      "target": {
        "type": "all",
        "conditions": [
          {
            "type": "item",
            "items": "yellow_stained_glass_pane"
          },
          {
            "type": "name",
            "mode": "equals",
            "name": [
              "Tank Level XXII",
              "Tank Level 22"
            ]
          }
        ]
      }
    },
    {
      "id": "skyblock_gui:classes/tank/locked/up_down",
      "target": {
        "type": "all",
        "conditions": [
          {
            "type": "item",
            "items": "red_stained_glass_pane"
          },
          {
            "type": "name",
            "mode": "equals",
            "name": [
              "Tank Level XXII",
              "Tank Level 22"
            ]
          }
        ]
      }
    },
    {
      "id": "skyblock_gui:classes/tank/unlocked/up_down",
      "target": {
        "type": "all",
        "conditions": [
          {
            "type": "item",
            "items": [
              "lime_stained_glass_pane"
            ]
          },
          {
            "type": "name",
            "mode": "equals",
            "name": [
              "Tank Level XXIII",
              "Tank Level 23"
            ]
          }
        ]
      }
    },
    {
      "id": "skyblock_gui:classes/tank/unlocking/up_down",
      "target": {
        "type": "all",
        "conditions": [
          {
            "type": "item",
            "items": "yellow_stained_glass_pane"
          },
          {
            "type": "name",
            "mode": "equals",
            "name": [
              "Tank Level XXIII",
              "Tank Level 23"
            ]
          }
        ]
      }
    },
    {
      "id": "skyblock_gui:classes/tank/locked/up_down",
      "target": {
        "type": "all",
        "conditions": [
          {
            "type": "item",
            "items": "red_stained_glass_pane"
          },
          {
            "type": "name",
            "mode": "equals",
            "name": [
              "Tank Level XXIII",
              "Tank Level 23"
            ]
          }
        ]
      }
    },
    {
      "id": "skyblock_gui:classes/tank/unlocked/up_down",
      "target": {
        "type": "all",
        "conditions": [
          {
            "type": "item",
            "items": [
              "lime_stained_glass_pane"
            ]
          },
          {
            "type": "name",
            "mode": "equals",
            "name": [
              "Tank Level XXIV",
              "Tank Level 24"
            ]
          }
        ]
      }
    },
    {
      "id": "skyblock_gui:classes/tank/unlocking/up_down",
      "target": {
        "type": "all",
        "conditions": [
          {
            "type": "item",
            "items": "yellow_stained_glass_pane"
          },
          {
            "type": "name",
            "mode": "equals",
            "name": [
              "Tank Level XXIV",
              "Tank Level 24"
            ]
          }
        ]
      }
    },
    {
      "id": "skyblock_gui:classes/tank/locked/up_down",
      "target": {
        "type": "all",
        "conditions": [
          {
            "type": "item",
            "items": "red_stained_glass_pane"
          },
          {
            "type": "name",
            "mode": "equals",
            "name": [
              "Tank Level XXIV",
              "Tank Level 24"
            ]
          }
        ]
      }
    },
    {
      "id": "skyblock_gui:classes/tank/unlocked/up_end",
      "target": {
        "type": "all",
        "conditions": [
          {
            "type": "item",
            "items": [
              "lime_stained_glass_pane",
              "leather_chestplate"
            ]
          },
          {
            "type": "name",
            "mode": "equals",
            "name": [
              "Tank Level XXV",
              "Tank Level 25"
            ]
          }
        ]
      }
    },
    {
      "id": "skyblock_gui:classes/tank/unlocking/up_end",
      "target": {
        "type": "all",
        "conditions": [
          {
            "type": "item",
            "items": "yellow_stained_glass_pane"
          },
          {
            "type": "name",
            "mode": "equals",
            "name": [
              "Tank Level XXV",
              "Tank Level 25"
            ]
          }
        ]
      }
    },
    {
      "id": "skyblock_gui:classes/tank/locked/up_end",
      "target": {
        "type": "all",
        "conditions": [
          {
            "type": "item",
            "items": "red_stained_glass_pane"
          },
          {
            "type": "name",
            "mode": "equals",
            "name": [
              "Tank Level XXV",
              "Tank Level 25"
            ]
          }
        ]
      }
    },
    {
      "id": "skyblock_gui:classes/tank/unlocked/start_down",
      "target": {
        "type": "all",
        "conditions": [
          {
            "type": "item",
            "items": [
              "lime_stained_glass_pane"
            ]
          },
          {
            "type": "name",
            "mode": "equals",
            "name": [
              "Tank Level XXVI",
              "Tank Level 26"
            ]
          }
        ]
      }
    },
    {
      "id": "skyblock_gui:classes/tank/unlocking/start_down",
      "target": {
        "type": "all",
        "conditions": [
          {
            "type": "item",
            "items": "yellow_stained_glass_pane"
          },
          {
            "type": "name",
            "mode": "equals",
            "name": [
              "Tank Level XXVI",
              "Tank Level 26"
            ]
          }
        ]
      }
    },
    {
      "id": "skyblock_gui:classes/tank/locked/start_down",
      "target": {
        "type": "all",
        "conditions": [
          {
            "type": "item",
            "items": "red_stained_glass_pane"
          },
          {
            "type": "name",
            "mode": "equals",
            "name": [
              "Tank Level XXVI",
              "Tank Level 26"
            ]
          }
        ]
      }
    },
    {
      "id": "skyblock_gui:classes/tank/unlocked/up_down",
      "target": {
        "type": "all",
        "conditions": [
          {
            "type": "item",
            "items": [
              "lime_stained_glass_pane"
            ]
          },
          {
            "type": "name",
            "mode": "equals",
            "name": [
              "Tank Level XXVII",
              "Tank Level 27"
            ]
          }
        ]
      }
    },
    {
      "id": "skyblock_gui:classes/tank/unlocking/up_down",
      "target": {
        "type": "all",
        "conditions": [
          {
            "type": "item",
            "items": "yellow_stained_glass_pane"
          },
          {
            "type": "name",
            "mode": "equals",
            "name": [
              "Tank Level XXVII",
              "Tank Level 27"
            ]
          }
        ]
      }
    },
    {
      "id": "skyblock_gui:classes/tank/locked/up_down",
      "target": {
        "type": "all",
        "conditions": [
          {
            "type": "item",
            "items": "red_stained_glass_pane"
          },
          {
            "type": "name",
            "mode": "equals",
            "name": [
              "Tank Level XXVII",
              "Tank Level 27"
            ]
          }
        ]
      }
    },
    {
      "id": "skyblock_gui:classes/tank/unlocked/up_right",
      "target": {
        "type": "all",
        "conditions": [
          {
            "type": "item",
            "items": [
              "lime_stained_glass_pane"
            ]
          },
          {
            "type": "name",
            "mode": "equals",
            "name": [
              "Tank Level XXVIII",
              "Tank Level 28"
            ]
          }
        ]
      }
    },
    {
      "id": "skyblock_gui:classes/tank/unlocking/up_right",
      "target": {
        "type": "all",
        "conditions": [
          {
            "type": "item",
            "items": "yellow_stained_glass_pane"
          },
          {
            "type": "name",
            "mode": "equals",
            "name": [
              "Tank Level XXVIII",
              "Tank Level 28"
            ]
          }
        ]
      }
    },
    {
      "id": "skyblock_gui:classes/tank/locked/up_right",
      "target": {
        "type": "all",
        "conditions": [
          {
            "type": "item",
            "items": "red_stained_glass_pane"
          },
          {
            "type": "name",
            "mode": "equals",
            "name": [
              "Tank Level XXVIII",
              "Tank Level 28"
            ]
          }
        ]
      }
    },
    {
      "id": "skyblock_gui:classes/tank/unlocked/left_right",
      "target": {
        "type": "all",
        "conditions": [
          {
            "type": "item",
            "items": [
              "lime_stained_glass_pane"
            ]
          },
          {
            "type": "name",
            "mode": "equals",
            "name": [
              "Tank Level XXIX",
              "Tank Level 29"
            ]
          }
        ]
      }
    },
    {
      "id": "skyblock_gui:classes/tank/unlocking/left_right",
      "target": {
        "type": "all",
        "conditions": [
          {
            "type": "item",
            "items": "yellow_stained_glass_pane"
          },
          {
            "type": "name",
            "mode": "equals",
            "name": [
              "Tank Level XXIX",
              "Tank Level 29"
            ]
          }
        ]
      }
    },
    {
      "id": "skyblock_gui:classes/tank/locked/left_right",
      "target": {
        "type": "all",
        "conditions": [
          {
            "type": "item",
            "items": "red_stained_glass_pane"
          },
          {
            "type": "name",
            "mode": "equals",
            "name": [
              "Tank Level XXIX",
              "Tank Level 29"
            ]
          }
        ]
      }
    },
    {
      "id": "skyblock_gui:classes/tank/unlocked/left_up",
      "target": {
        "type": "all",
        "conditions": [
          {
            "type": "item",
            "items": [
              "lime_stained_glass_pane",
              "leather_chestplate"
            ]
          },
          {
            "type": "name",
            "mode": "equals",
            "name": [
              "Tank Level XXX",
              "Tank Level 30"
            ]
          }
        ]
      }
    },
    {
      "id": "skyblock_gui:classes/tank/unlocking/left_up",
      "target": {
        "type": "all",
        "conditions": [
          {
            "type": "item",
            "items": "yellow_stained_glass_pane"
          },
          {
            "type": "name",
            "mode": "equals",
            "name": [
              "Tank Level XXX",
              "Tank Level 30"
            ]
          }
        ]
      }
    },
    {
      "id": "skyblock_gui:classes/tank/locked/left_up",
      "target": {
        "type": "all",
        "conditions": [
          {
            "type": "item",
            "items": "red_stained_glass_pane"
          },
          {
            "type": "name",
            "mode": "equals",
            "name": [
              "Tank Level XXX",
              "Tank Level 30"
            ]
          }
        ]
      }
    },
    {
      "id": "skyblock_gui:classes/tank/unlocked/down_up",
      "target": {
        "type": "all",
        "conditions": [
          {
            "type": "item",
            "items": [
              "lime_stained_glass_pane"
            ]
          },
          {
            "type": "name",
            "mode": "equals",
            "name": [
              "Tank Level XXXI",
              "Tank Level 31"
            ]
          }
        ]
      }
    },
    {
      "id": "skyblock_gui:classes/tank/unlocking/down_up",
      "target": {
        "type": "all",
        "conditions": [
          {
            "type": "item",
            "items": "yellow_stained_glass_pane"
          },
          {
            "type": "name",
            "mode": "equals",
            "name": [
              "Tank Level XXXI",
              "Tank Level 31"
            ]
          }
        ]
      }
    },
    {
      "id": "skyblock_gui:classes/tank/locked/down_up",
      "target": {
        "type": "all",
        "conditions": [
          {
            "type": "item",
            "items": "red_stained_glass_pane"
          },
          {
            "type": "name",
            "mode": "equals",
            "name": [
              "Tank Level XXXI",
              "Tank Level 31"
            ]
          }
        ]
      }
    },
    {
      "id": "skyblock_gui:classes/tank/unlocked/down_up",
      "target": {
        "type": "all",
        "conditions": [
          {
            "type": "item",
            "items": [
              "lime_stained_glass_pane"
            ]
          },
          {
            "type": "name",
            "mode": "equals",
            "name": [
              "Tank Level XXXII",
              "Tank Level 32"
            ]
          }
        ]
      }
    },
    {
      "id": "skyblock_gui:classes/tank/unlocking/down_up",
      "target": {
        "type": "all",
        "conditions": [
          {
            "type": "item",
            "items": "yellow_stained_glass_pane"
          },
          {
            "type": "name",
            "mode": "equals",
            "name": [
              "Tank Level XXXII",
              "Tank Level 32"
            ]
          }
        ]
      }
    },
    {
      "id": "skyblock_gui:classes/tank/locked/down_up",
      "target": {
        "type": "all",
        "conditions": [
          {
            "type": "item",
            "items": "red_stained_glass_pane"
          },
          {
            "type": "name",
            "mode": "equals",
            "name": [
              "Tank Level XXXII",
              "Tank Level 32"
            ]
          }
        ]
      }
    },
    {
      "id": "skyblock_gui:classes/tank/unlocked/down_right",
      "target": {
        "type": "all",
        "conditions": [
          {
            "type": "item",
            "items": [
              "lime_stained_glass_pane"
            ]
          },
          {
            "type": "name",
            "mode": "equals",
            "name": [
              "Tank Level XXXIII",
              "Tank Level 33"
            ]
          }
        ]
      }
    },
    {
      "id": "skyblock_gui:classes/tank/unlocking/down_right",
      "target": {
        "type": "all",
        "conditions": [
          {
            "type": "item",
            "items": "yellow_stained_glass_pane"
          },
          {
            "type": "name",
            "mode": "equals",
            "name": [
              "Tank Level XXXIII",
              "Tank Level 33"
            ]
          }
        ]
      }
    },
    {
      "id": "skyblock_gui:classes/tank/locked/down_right",
      "target": {
        "type": "all",
        "conditions": [
          {
            "type": "item",
            "items": "red_stained_glass_pane"
          },
          {
            "type": "name",
            "mode": "equals",
            "name": [
              "Tank Level XXXIII",
              "Tank Level 33"
            ]
          }
        ]
      }
    },
    {
      "id": "skyblock_gui:classes/tank/unlocked/left_right",
      "target": {
        "type": "all",
        "conditions": [
          {
            "type": "item",
            "items": [
              "lime_stained_glass_pane"
            ]
          },
          {
            "type": "name",
            "mode": "equals",
            "name": [
              "Tank Level XXXIV",
              "Tank Level 34"
            ]
          }
        ]
      }
    },
    {
      "id": "skyblock_gui:classes/tank/unlocking/left_right",
      "target": {
        "type": "all",
        "conditions": [
          {
            "type": "item",
            "items": "yellow_stained_glass_pane"
          },
          {
            "type": "name",
            "mode": "equals",
            "name": [
              "Tank Level XXXIV",
              "Tank Level 34"
            ]
          }
        ]
      }
    },
    {
      "id": "skyblock_gui:classes/tank/locked/left_right",
      "target": {
        "type": "all",
        "conditions": [
          {
            "type": "item",
            "items": "red_stained_glass_pane"
          },
          {
            "type": "name",
            "mode": "equals",
            "name": [
              "Tank Level XXXIV",
              "Tank Level 34"
            ]
          }
        ]
      }
    },
    {
      "id": "skyblock_gui:classes/tank/unlocked/left_down",
      "target": {
        "type": "all",
        "conditions": [
          {
            "type": "item",
            "items": [
              "lime_stained_glass_pane",
              "leather_chestplate"
            ]
          },
          {
            "type": "name",
            "mode": "equals",
            "name": [
              "Tank Level XXXV",
              "Tank Level 35"
            ]
          }
        ]
      }
    },
    {
      "id": "skyblock_gui:classes/tank/unlocking/left_down",
      "target": {
        "type": "all",
        "conditions": [
          {
            "type": "item",
            "items": "yellow_stained_glass_pane"
          },
          {
            "type": "name",
            "mode": "equals",
            "name": [
              "Tank Level XXXV",
              "Tank Level 35"
            ]
          }
        ]
      }
    },
    {
      "id": "skyblock_gui:classes/tank/locked/left_down",
      "target": {
        "type": "all",
        "conditions": [
          {
            "type": "item",
            "items": "red_stained_glass_pane"
          },
          {
            "type": "name",
            "mode": "equals",
            "name": [
              "Tank Level XXXV",
              "Tank Level 35"
            ]
          }
        ]
      }
    },
    {
      "id": "skyblock_gui:classes/tank/unlocked/up_down",
      "target": {
        "type": "all",
        "conditions": [
          {
            "type": "item",
            "items": [
              "lime_stained_glass_pane"
            ]
          },
          {
            "type": "name",
            "mode": "equals",
            "name": [
              "Tank Level XXXVI",
              "Tank Level 36"
            ]
          }
        ]
      }
    },
    {
      "id": "skyblock_gui:classes/tank/unlocking/up_down",
      "target": {
        "type": "all",
        "conditions": [
          {
            "type": "item",
            "items": "yellow_stained_glass_pane"
          },
          {
            "type": "name",
            "mode": "equals",
            "name": [
              "Tank Level XXXVI",
              "Tank Level 36"
            ]
          }
        ]
      }
    },
    {
      "id": "skyblock_gui:classes/tank/locked/up_down",
      "target": {
        "type": "all",
        "conditions": [
          {
            "type": "item",
            "items": "red_stained_glass_pane"
          },
          {
            "type": "name",
            "mode": "equals",
            "name": [
              "Tank Level XXXVI",
              "Tank Level 36"
            ]
          }
        ]
      }
    },
    {
      "id": "skyblock_gui:classes/tank/unlocked/up_down",
      "target": {
        "type": "all",
        "conditions": [
          {
            "type": "item",
            "items": [
              "lime_stained_glass_pane"
            ]
          },
          {
            "type": "name",
            "mode": "equals",
            "name": [
              "Tank Level XXXVII",
              "Tank Level 37"
            ]
          }
        ]
      }
    },
    {
      "id": "skyblock_gui:classes/tank/unlocking/up_down",
      "target": {
        "type": "all",
        "conditions": [
          {
            "type": "item",
            "items": "yellow_stained_glass_pane"
          },
          {
            "type": "name",
            "mode": "equals",
            "name": [
              "Tank Level XXXVII",
              "Tank Level 37"
            ]
          }
        ]
      }
    },
    {
      "id": "skyblock_gui:classes/tank/locked/up_down",
      "target": {
        "type": "all",
        "conditions": [
          {
            "type": "item",
            "items": "red_stained_glass_pane"
          },
          {
            "type": "name",
            "mode": "equals",
            "name": [
              "Tank Level XXXVII",
              "Tank Level 37"
            ]
          }
        ]
      }
    },
    {
      "id": "skyblock_gui:classes/tank/unlocked/up_right",
      "target": {
        "type": "all",
        "conditions": [
          {
            "type": "item",
            "items": [
              "lime_stained_glass_pane"
            ]
          },
          {
            "type": "name",
            "mode": "equals",
            "name": [
              "Tank Level XXXVIII",
              "Tank Level 38"
            ]
          }
        ]
      }
    },
    {
      "id": "skyblock_gui:classes/tank/unlocking/up_right",
      "target": {
        "type": "all",
        "conditions": [
          {
            "type": "item",
            "items": "yellow_stained_glass_pane"
          },
          {
            "type": "name",
            "mode": "equals",
            "name": [
              "Tank Level XXXVIII",
              "Tank Level 38"
            ]
          }
        ]
      }
    },
    {
      "id": "skyblock_gui:classes/tank/locked/up_right",
      "target": {
        "type": "all",
        "conditions": [
          {
            "type": "item",
            "items": "red_stained_glass_pane"
          },
          {
            "type": "name",
            "mode": "equals",
            "name": [
              "Tank Level XXXVIII",
              "Tank Level 38"
            ]
          }
        ]
      }
    },
    {
      "id": "skyblock_gui:classes/tank/unlocked/left_right",
      "target": {
        "type": "all",
        "conditions": [
          {
            "type": "item",
            "items": [
              "lime_stained_glass_pane"
            ]
          },
          {
            "type": "name",
            "mode": "equals",
            "name": [
              "Tank Level XXXIX",
              "Tank Level 39"
            ]
          }
        ]
      }
    },
    {
      "id": "skyblock_gui:classes/tank/unlocking/left_right",
      "target": {
        "type": "all",
        "conditions": [
          {
            "type": "item",
            "items": "yellow_stained_glass_pane"
          },
          {
            "type": "name",
            "mode": "equals",
            "name": [
              "Tank Level XXXIX",
              "Tank Level 39"
            ]
          }
        ]
      }
    },
    {
      "id": "skyblock_gui:classes/tank/locked/left_right",
      "target": {
        "type": "all",
        "conditions": [
          {
            "type": "item",
            "items": "red_stained_glass_pane"
          },
          {
            "type": "name",
            "mode": "equals",
            "name": [
              "Tank Level XXXIX",
              "Tank Level 39"
            ]
          }
        ]
      }
    },
    {
      "id": "skyblock_gui:classes/tank/unlocked/left_up",
      "target": {
        "type": "all",
        "conditions": [
          {
            "type": "item",
            "items": [
              "lime_stained_glass_pane",
              "leather_chestplate"
            ]
          },
          {
            "type": "name",
            "mode": "equals",
            "name": [
              "Tank Level XL",
              "Tank Level 40"
            ]
          }
        ]
      }
    },
    {
      "id": "skyblock_gui:classes/tank/unlocking/left_up",
      "target": {
        "type": "all",
        "conditions": [
          {
            "type": "item",
            "items": "yellow_stained_glass_pane"
          },
          {
            "type": "name",
            "mode": "equals",
            "name": [
              "Tank Level XL",
              "Tank Level 40"
            ]
          }
        ]
      }
    },
    {
      "id": "skyblock_gui:classes/tank/locked/left_up",
      "target": {
        "type": "all",
        "conditions": [
          {
            "type": "item",
            "items": "red_stained_glass_pane"
          },
          {
            "type": "name",
            "mode": "equals",
            "name": [
              "Tank Level XL",
              "Tank Level 40"
            ]
          }
        ]
      }
    },
    {
      "id": "skyblock_gui:classes/tank/unlocked/down_up",
      "target": {
        "type": "all",
        "conditions": [
          {
            "type": "item",
            "items": [
              "lime_stained_glass_pane"
            ]
          },
          {
            "type": "name",
            "mode": "equals",
            "name": [
              "Tank Level XLI",
              "Tank Level 41"
            ]
          }
        ]
      }
    },
    {
      "id": "skyblock_gui:classes/tank/unlocking/down_up",
      "target": {
        "type": "all",
        "conditions": [
          {
            "type": "item",
            "items": "yellow_stained_glass_pane"
          },
          {
            "type": "name",
            "mode": "equals",
            "name": [
              "Tank Level XLI",
              "Tank Level 41"
            ]
          }
        ]
      }
    },
    {
      "id": "skyblock_gui:classes/tank/locked/down_up",
      "target": {
        "type": "all",
        "conditions": [
          {
            "type": "item",
            "items": "red_stained_glass_pane"
          },
          {
            "type": "name",
            "mode": "equals",
            "name": [
              "Tank Level XLI",
              "Tank Level 41"
            ]
          }
        ]
      }
    },
    {
      "id": "skyblock_gui:classes/tank/unlocked/down_up",
      "target": {
        "type": "all",
        "conditions": [
          {
            "type": "item",
            "items": [
              "lime_stained_glass_pane"
            ]
          },
          {
            "type": "name",
            "mode": "equals",
            "name": [
              "Tank Level XLII",
              "Tank Level 42"
            ]
          }
        ]
      }
    },
    {
      "id": "skyblock_gui:classes/tank/unlocking/down_up",
      "target": {
        "type": "all",
        "conditions": [
          {
            "type": "item",
            "items": "yellow_stained_glass_pane"
          },
          {
            "type": "name",
            "mode": "equals",
            "name": [
              "Tank Level XLII",
              "Tank Level 42"
            ]
          }
        ]
      }
    },
    {
      "id": "skyblock_gui:classes/tank/locked/down_up",
      "target": {
        "type": "all",
        "conditions": [
          {
            "type": "item",
            "items": "red_stained_glass_pane"
          },
          {
            "type": "name",
            "mode": "equals",
            "name": [
              "Tank Level XLII",
              "Tank Level 42"
            ]
          }
        ]
      }
    },
    {
      "id": "skyblock_gui:classes/tank/unlocked/down_right",
      "target": {
        "type": "all",
        "conditions": [
          {
            "type": "item",
            "items": [
              "lime_stained_glass_pane"
            ]
          },
          {
            "type": "name",
            "mode": "equals",
            "name": [
              "Tank Level XLIII",
              "Tank Level 43"
            ]
          }
        ]
      }
    },
    {
      "id": "skyblock_gui:classes/tank/unlocking/down_right",
      "target": {
        "type": "all",
        "conditions": [
          {
            "type": "item",
            "items": "yellow_stained_glass_pane"
          },
          {
            "type": "name",
            "mode": "equals",
            "name": [
              "Tank Level XLIII",
              "Tank Level 43"
            ]
          }
        ]
      }
    },
    {
      "id": "skyblock_gui:classes/tank/locked/down_right",
      "target": {
        "type": "all",
        "conditions": [
          {
            "type": "item",
            "items": "red_stained_glass_pane"
          },
          {
            "type": "name",
            "mode": "equals",
            "name": [
              "Tank Level XLIII",
              "Tank Level 43"
            ]
          }
        ]
      }
    },
    {
      "id": "skyblock_gui:classes/tank/unlocked/left_right",
      "target": {
        "type": "all",
        "conditions": [
          {
            "type": "item",
            "items": [
              "lime_stained_glass_pane"
            ]
          },
          {
            "type": "name",
            "mode": "equals",
            "name": [
              "Tank Level XLIV",
              "Tank Level 44"
            ]
          }
        ]
      }
    },
    {
      "id": "skyblock_gui:classes/tank/unlocking/left_right",
      "target": {
        "type": "all",
        "conditions": [
          {
            "type": "item",
            "items": "yellow_stained_glass_pane"
          },
          {
            "type": "name",
            "mode": "equals",
            "name": [
              "Tank Level XLIV",
              "Tank Level 44"
            ]
          }
        ]
      }
    },
    {
      "id": "skyblock_gui:classes/tank/locked/left_right",
      "target": {
        "type": "all",
        "conditions": [
          {
            "type": "item",
            "items": "red_stained_glass_pane"
          },
          {
            "type": "name",
            "mode": "equals",
            "name": [
              "Tank Level XLIV",
              "Tank Level 44"
            ]
          }
        ]
      }
    },
    {
      "id": "skyblock_gui:classes/tank/unlocked/left_down",
      "target": {
        "type": "all",
        "conditions": [
          {
            "type": "item",
            "items": [
              "lime_stained_glass_pane",
              "leather_chestplate"
            ]
          },
          {
            "type": "name",
            "mode": "equals",
            "name": [
              "Tank Level XLV",
              "Tank Level 45"
            ]
          }
        ]
      }
    },
    {
      "id": "skyblock_gui:classes/tank/unlocking/left_down",
      "target": {
        "type": "all",
        "conditions": [
          {
            "type": "item",
            "items": "yellow_stained_glass_pane"
          },
          {
            "type": "name",
            "mode": "equals",
            "name": [
              "Tank Level XLV",
              "Tank Level 45"
            ]
          }
        ]
      }
    },
    {
      "id": "skyblock_gui:classes/tank/locked/left_down",
      "target": {
        "type": "all",
        "conditions": [
          {
            "type": "item",
            "items": "red_stained_glass_pane"
          },
          {
            "type": "name",
            "mode": "equals",
            "name": [
              "Tank Level XLV",
              "Tank Level 45"
            ]
          }
        ]
      }
    },
    {
      "id": "skyblock_gui:classes/tank/unlocked/up_down",
      "target": {
        "type": "all",
        "conditions": [
          {
            "type": "item",
            "items": [
              "lime_stained_glass_pane"
            ]
          },
          {
            "type": "name",
            "mode": "equals",
            "name": [
              "Tank Level XLVI",
              "Tank Level 46"
            ]
          }
        ]
      }
    },
    {
      "id": "skyblock_gui:classes/tank/unlocking/up_down",
      "target": {
        "type": "all",
        "conditions": [
          {
            "type": "item",
            "items": "yellow_stained_glass_pane"
          },
          {
            "type": "name",
            "mode": "equals",
            "name": [
              "Tank Level XLVI",
              "Tank Level 46"
            ]
          }
        ]
      }
    },
    {
      "id": "skyblock_gui:classes/tank/locked/up_down",
      "target": {
        "type": "all",
        "conditions": [
          {
            "type": "item",
            "items": "red_stained_glass_pane"
          },
          {
            "type": "name",
            "mode": "equals",
            "name": [
              "Tank Level XLVI",
              "Tank Level 46"
            ]
          }
        ]
      }
    },
    {
      "id": "skyblock_gui:classes/tank/unlocked/up_down",
      "target": {
        "type": "all",
        "conditions": [
          {
            "type": "item",
            "items": [
              "lime_stained_glass_pane"
            ]
          },
          {
            "type": "name",
            "mode": "equals",
            "name": [
              "Tank Level XLVII",
              "Tank Level 47"
            ]
          }
        ]
      }
    },
    {
      "id": "skyblock_gui:classes/tank/unlocking/up_down",
      "target": {
        "type": "all",
        "conditions": [
          {
            "type": "item",
            "items": "yellow_stained_glass_pane"
          },
          {
            "type": "name",
            "mode": "equals",
            "name": [
              "Tank Level XLVII",
              "Tank Level 47"
            ]
          }
        ]
      }
    },
    {
      "id": "skyblock_gui:classes/tank/locked/up_down",
      "target": {
        "type": "all",
        "conditions": [
          {
            "type": "item",
            "items": "red_stained_glass_pane"
          },
          {
            "type": "name",
            "mode": "equals",
            "name": [
              "Tank Level XLVII",
              "Tank Level 47"
            ]
          }
        ]
      }
    },
    {
      "id": "skyblock_gui:classes/tank/unlocked/up_down",
      "target": {
        "type": "all",
        "conditions": [
          {
            "type": "item",
            "items": [
              "lime_stained_glass_pane"
            ]
          },
          {
            "type": "name",
            "mode": "equals",
            "name": [
              "Tank Level XLVIII",
              "Tank Level 48"
            ]
          }
        ]
      }
    },
    {
      "id": "skyblock_gui:classes/tank/unlocking/up_down",
      "target": {
        "type": "all",
        "conditions": [
          {
            "type": "item",
            "items": "yellow_stained_glass_pane"
          },
          {
            "type": "name",
            "mode": "equals",
            "name": [
              "Tank Level XLVIII",
              "Tank Level 48"
            ]
          }
        ]
      }
    },
    {
      "id": "skyblock_gui:classes/tank/locked/up_down",
      "target": {
        "type": "all",
        "conditions": [
          {
            "type": "item",
            "items": "red_stained_glass_pane"
          },
          {
            "type": "name",
            "mode": "equals",
            "name": [
              "Tank Level XLVIII",
              "Tank Level 48"
            ]
          }
        ]
      }
    },
    {
      "id": "skyblock_gui:classes/tank/unlocked/up_down",
      "target": {
        "type": "all",
        "conditions": [
          {
            "type": "item",
            "items": [
              "lime_stained_glass_pane"
            ]
          },
          {
            "type": "name",
            "mode": "equals",
            "name": [
              "Tank Level XLIX",
              "Tank Level 49"
            ]
          }
        ]
      }
    },
    {
      "id": "skyblock_gui:classes/tank/unlocking/up_down",
      "target": {
        "type": "all",
        "conditions": [
          {
            "type": "item",
            "items": "yellow_stained_glass_pane"
          },
          {
            "type": "name",
            "mode": "equals",
            "name": [
              "Tank Level XLIX",
              "Tank Level 49"
            ]
          }
        ]
      }
    },
    {
      "id": "skyblock_gui:classes/tank/locked/up_down",
      "target": {
        "type": "all",
        "conditions": [
          {
            "type": "item",
            "items": "red_stained_glass_pane"
          },
          {
            "type": "name",
            "mode": "equals",
            "name": [
              "Tank Level XLIX",
              "Tank Level 49"
            ]
          }
        ]
      }
    },
    {
      "id": "skyblock_gui:classes/tank/unlocked/up_end",
      "target": {
        "type": "all",
        "conditions": [
          {
            "type": "item",
            "items": [
              "lime_stained_glass_pane",
              "leather_chestplate"
            ]
          },
          {
            "type": "name",
            "mode": "equals",
            "name": [
              "Tank Level L",
              "Tank Level 50"
            ]
          }
        ]
      }
    },
    {
      "id": "skyblock_gui:classes/tank/unlocking/up_end",
      "target": {
        "type": "all",
        "conditions": [
          {
            "type": "item",
            "items": "yellow_stained_glass_pane"
          },
          {
            "type": "name",
            "mode": "equals",
            "name": [
              "Tank Level L",
              "Tank Level 50"
            ]
          }
        ]
      }
    },
    {
      "id": "skyblock_gui:classes/tank/locked/up_end",
      "target": {
        "type": "all",
        "conditions": [
          {
            "type": "item",
            "items": "red_stained_glass_pane"
          },
          {
            "type": "name",
            "mode": "equals",
            "name": [
              "Tank Level L",
              "Tank Level 50"
            ]
          }
        ]
      }
    }
  ]
}